neattime/__init__.py
neattime/neattime.py
neattime-0.0.4.dist-info/METADATA
neattime-0.0.4.dist-info/WHEEL
neattime-0.0.4.dist-info/licenses/LICENSE
neattime-0.0.4.dist-info/RECORD
