Metadata-Version: 2.4
Name: neattime
Version: 0.0.4
Summary: A single function to get a nice date-time format
Project-URL: Homepage, https://github.com/cgeils25/neattime
Project-URL: Issues, https://github.com/cgeils25/neattime/issues
Author-email: Christian Geils <christiangeils@outlook.com>
Maintainer-email: Christian Geils <christiangeils@outlook.com>
License-Expression: MIT
License-File: LICENSE
Classifier: Operating System :: OS Independent
Classifier: Programming Language :: Python :: 3
Requires-Python: >=3.8
